{"id":69907,"date":"2023-03-03T12:32:48","date_gmt":"2023-03-03T12:32:48","guid":{"rendered":"https:\/\/staging.goskydive.com\/?post_type=charity&#038;p=69907"},"modified":"2023-03-09T14:02:19","modified_gmt":"2023-03-09T14:02:19","slug":"freedom-in-christ-ministries-uk","status":"publish","type":"charity","link":"https:\/\/www.goskydive.com\/charity\/freedom-in-christ-ministries-uk\/","title":{"rendered":"Freedom In Christ Ministries UK"},"content":{"rendered":"","protected":false},"excerpt":{"rendered":"","protected":false},"featured_media":0,"menu_order":0,"template":"","meta":[],"acf":[],"_links":{"self":[{"href":"https:\/\/www.goskydive.com\/wp-json\/wp\/v2\/charity\/69907"}],"collection":[{"href":"https:\/\/www.goskydive.com\/wp-json\/wp\/v2\/charity"}],"about":[{"href":"https:\/\/www.goskydive.com\/wp-json\/wp\/v2\/types\/charity"}],"wp:attachment":[{"href":"https:\/\/www.goskydive.com\/wp-json\/wp\/v2\/media?parent=69907"}],"curies":[{"name":"wp","href":"https:\/\/api.w.org\/{rel}","templated":true}]}}